{"js":"javascript","c#":"c#","java":"java","javascript":"javascript","php":"php","android":"android","jquery":"jquery","c++":"c++","python":"python","html":"html","mysql":"mysql","asp.net":"asp.net","iphone":"iphone","ios":"ios",".net":".net","css":"css","sql":"sql","objective c":"objective-c","objective-c":"objective-c","ruby on rails":"ruby-on-rails","ruby-on-rails":"ruby-on-rails","c":"c","ruby":"ruby","sql server":"sql-server","sql-server":"sql-server","xml":"xml","ajax":"ajax","wpf":"wpf","regex":"regex","asp.net mvc":"asp.net-mvc","asp.net-mvc":"asp.net-mvc","arrays":"arrays","database":"database","django":"django","linux":"linux","xcode":"xcode","json":"json","windows":"windows","vb.net":"vb.net","eclipse":"eclipse","facebook":"facebook","ruby on rails 3":"ruby-on-rails-3","ruby-on-rails-3":"ruby-on-rails-3","multithreading":"multithreading","html5":"html5","winforms":"winforms","r":"r","wordpress":"wordpress","visual studio 2010":"visual-studio-2010","visual-studio-2010":"visual-studio-2010","performance":"performance","asp.net mvc 3":"asp.net-mvc-3","asp.net-mvc-3":"asp.net-mvc-3","osx":"osx","spring":"spring","algorithm":"algorithm","linq":"linq","oracle":"oracle","wcf":"wcf","swing":"swing","git":"git","web services":"web-services","web-services":"web-services","excel":"excel","perl":"perl","sql server 2008":"sql-server-2008","sql-server-2008":"sql-server-2008","visual studio":"visual-studio","visual-studio":"visual-studio","node":"nodejs","node-js":"nodejs","node.js":"nodejs","node js":"nodejs","nodejs":"nodejs","apache":"apache","actionscript 3":"actionscript-3","actionscript-3":"actionscript-3","entity framework":"entity-framework","entity-framework":"entity-framework","hibernate":"hibernate","ipad":"ipad","cocoa touch":"cocoa-touch","cocoa-touch":"cocoa-touch","bash":"bash","cocoa":"cocoa","flash":"flash","silverlight":"silverlight","api":"api","qt":"qt","jquery ui":"jquery-ui","jquery-ui":"jquery-ui","sqlite":"sqlite","matlab":"matlab","tsql":"tsql",".htaccess":".htaccess","delphi":"delphi","codeigniter":"codeigniter","security":"security","internet explorer":"internet-explorer","internet-explorer":"internet-explorer","flex":"flex","google app engine":"google-app-engine","google-app-engine":"google-app-engine","oop":"oop","mongodb":"mongodb","jsp":"jsp","unit testing":"unit-testing","unit-testing":"unit-testing","postgresql":"postgresql","google maps":"google-maps","google-maps":"google-maps","css3":"css3","validation":"validation","sockets":"sockets","shell":"shell","parsing":"parsing","debugging":"debugging","http":"http","scala":"scala","xaml":"xaml","vba":"vba","magento":"magento","windows phone 7":"windows-phone-7","windows-phone-7":"windows-phone-7","google chrome":"google-chrome","google-chrome":"google-chrome","winapi":"winapi","android layout":"android-layout","android-layout":"android-layout","uitableview":"uitableview","jquery ajax":"jquery-ajax","jquery-ajax":"jquery-ajax","rest":"rest","jsf":"jsf","templates":"templates","events":"events","svn":"svn","maven":"maven","c# 4.0":"c#-4.0","c#-4.0":"c#-4.0","session":"session","asp.net mvc 4":"asp.net-mvc-4","asp.net-mvc-4":"asp.net-mvc-4","sql server 2005":"sql-server-2005","sql-server-2005":"sql-server-2005","zend framework":"zend-framework","zend-framework":"zend-framework","facebook graph api":"facebook-graph-api","facebook-graph-api":"facebook-graph-api","cakephp":"cakephp","unix":"unix","firefox":"firefox","visual c++":"visual-c++","visual-c++":"visual-c++","java ee":"java-ee","java-ee":"java-ee","jquery mobile":"jquery-mobile","jquery-mobile":"jquery-mobile","ms access":"ms-access","ms-access":"ms-access","nhibernate":"nhibernate","datetime":"datetime","twitter bootstrap":"twitter-bootstrap","twitter-bootstrap":"twitter-bootstrap","visual studio 2008":"visual-studio-2008","visual-studio-2008":"visual-studio-2008","search":"search","tomcat":"tomcat","gwt":"gwt","sharepoint":"sharepoint","xslt":"xslt","authentication":"authentication","angular":"angularjs","angular-js":"angularjs","angular.js":"angularjs","angular js":"angularjs","angularjs":"angularjs","design patterns":"design-patterns","design-patterns":"design-patterns","opengl":"opengl","google":"google","math":"math","caching":"caching","pointers":"pointers","iis":"iis","symfony2":"symfony2","servlets":"servlets","testing":"testing","pdf":"pdf","grails":"grails","animation":"animation","opencv":"opencv","spring mvc":"spring-mvc","spring-mvc":"spring-mvc","design":"design","post":"post","mod rewrite":"mod-rewrite","mod-rewrite":"mod-rewrite","haskell":"haskell","core data":"core-data","core-data":"core-data","drupal":"drupal","inheritance":"inheritance","web applications":"web-applications","web-applications":"web-applications","powershell":"powershell","mobile":"mobile","memory":"memory","phonegap":"phonegap","jpa":"jpa","batch file":"batch-file","batch-file":"batch-file","optimization":"optimization","mvc":"mvc","activerecord":"activerecord","layout":"layout","ubuntu":"ubuntu","database design":"database-design","database-design":"database-design","ios5":"ios5","audio":"audio","gcc":"gcc","iframe":"iframe","ext":"extjs","ext-js":"extjs","ext.js":"extjs","ext js":"extjs","extjs":"extjs","gridview":"gridview","logging":"logging","stored procedures":"stored-procedures","stored-procedures":"stored-procedures","vim":"vim","backbone":"backbonejs","backbone-js":"backbonejs","backbone.js":"backbonejs","backbone js":"backbonejs","backbonejs":"backbonejs","video":"video","linq to sql":"linq-to-sql","linq-to-sql":"linq-to-sql","serialization":"serialization","gui":"gui","memory management":"memory-management","memory-management":"memory-management","image processing":"image-processing","image-processing":"image-processing","user interface":"user-interface","user-interface":"user-interface","csv":"csv","ios4":"ios4","android intent":"android-intent","android-intent":"android-intent","python 2.7":"python-2.7","python-2.7":"python-2.7","razor":"razor","visual studio 2012":"visual-studio-2012","visual-studio-2012":"visual-studio-2012","excel vba":"excel-vba","excel-vba":"excel-vba","file upload":"file-upload","file-upload":"file-upload","data binding":"data-binding","data-binding":"data-binding","boost":"boost","cookies":"cookies","soap":"soap","plugins":"plugins","azure":"azure","curl":"curl","jsf 2":"jsf-2","jsf-2":"jsf-2","reflection":"reflection","assembly":"assembly","ssl":"ssl","canvas":"canvas","dll":"dll","jquery plugins":"jquery-plugins","jquery-plugins":"jquery-plugins","google maps api 3":"google-maps-api-3","google-maps-api-3":"google-maps-api-3","netbeans":"netbeans","xpath":"xpath","encryption":"encryption","heroku":"heroku","mvvm":"mvvm","selenium":"selenium","jdbc":"jdbc","twitter":"twitter","deployment":"deployment","javascript events":"javascript-events","javascript-events":"javascript-events","asynchronous":"asynchronous","data structures":"data-structures","data-structures":"data-structures","c++11":"c++11","ios6":"ios6","emacs":"emacs","drop down menu":"drop-down-menu","drop-down-menu":"drop-down-menu","asp.net mvc 2":"asp.net-mvc-2","asp.net-mvc-2":"asp.net-mvc-2","version control":"version-control","version-control":"version-control","hadoop":"hadoop","windows 8":"windows-8","windows-8":"windows-8","blackberry":"blackberry","ember":"emberjs","ember-js":"emberjs","ember.js":"emberjs","ember js":"emberjs","emberjs":"emberjs","d3":"d3","knockout":"knockoutjs","knockout-js":"knockoutjs","knockout.js":"knockoutjs","knockout js":"knockoutjs","knockoutjs":"knockoutjs","framework":"framework","regular expression":"regular-expression","regular-expression":"regular-expression","aws":"aws","redis":"redis","mongo":"mongo","meteor":"meteor"}